tiledimage/2pngs.py
tiledimage/__init__.py
tiledimage/cachedimage.py
tiledimage/pngs2.py
tiledimage/tilecache.py
tiledimage/tiledimage.py
tiledimage-0.4.dist-info/METADATA
tiledimage-0.4.dist-info/WHEEL
tiledimage-0.4.dist-info/entry_points.txt
tiledimage-0.4.dist-info/RECORD
