Metadata-Version: 2.1
Name: tiledimage
Version: 0.4
Summary: tools for tiled image that can be cached on a filesystem.
License: MIT
Author: vitroid
Author-email: vitroid@gmail.com
Requires-Python: >=3.10,<4.0
Classifier: License :: OSI Approved :: MIT License
Classifier: Programming Language :: Python :: 3
Classifier: Programming Language :: Python :: 3.10
Classifier: Programming Language :: Python :: 3.11
Classifier: Programming Language :: Python :: 3.12
Requires-Dist: opencv-python-headless (>=4.11.0.86,<5.0.0.0)
Requires-Dist: pylru (>=1.2.1,<2.0.0)
